instarchive.py
instarchive-1.0.2.dist-info/LICENSE
instarchive-1.0.2.dist-info/METADATA
instarchive-1.0.2.dist-info/WHEEL
instarchive-1.0.2.dist-info/entry_points.txt
instarchive-1.0.2.dist-info/top_level.txt
instarchive-1.0.2.dist-info/RECORD
