Metadata-Version: 2.1
Name: instarchive
Version: 1.0.2
Summary: CLI tool for collecting and archiving data from Instagram users with Instaloader.
Author-email: Expertcoderz <expertcoderzx@gmail.com>
Project-URL: Homepage, https://github.com/Expertcoderz/instarchive
Project-URL: Repository, https://github.com/Expertcoderz/instarchive.git
Project-URL: Issues, https://github.com/Expertcoderz/instarchive/issues
Keywords: instagram,instagram-scraper,instagram-client,instagram-feed,downloader,videos,photos,pictures,instagram-user-photos,instagram-photos,instagram-metadata,instagram-downloader,instagram-stories
Classifier: Development Status :: 5 - Production/Stable
Classifier: Environment :: Console
Classifier: Intended Audience :: Developers
Classifier: Intended Audience :: End Users/Desktop
Classifier: License :: OSI Approved :: MIT License
Classifier: Operating System :: OS Independent
Classifier: Programming Language :: Python :: 3.12
Classifier: Programming Language :: Python :: 3 :: Only
Classifier: Topic :: Internet
Classifier: Topic :: Multimedia :: Graphics
Requires-Python: >=3.12
License-File: LICENSE
Requires-Dist: click >=8.1.7
Requires-Dist: instaloader >=4.11
